wasm_spec_kernel/__init__.py
wasm_spec_kernel/__main__.py
wasm_spec_kernel/defs.py
wasm_spec_kernel/install.py
wasm_spec_kernel/kernel.py
wasm_spec_kernel/wasm_replwrap.py
wasm_spec_kernel-0.1.1.dist-info/LICENSE
wasm_spec_kernel-0.1.1.dist-info/WHEEL
wasm_spec_kernel-0.1.1.dist-info/METADATA
wasm_spec_kernel-0.1.1.dist-info/RECORD
