Metadata-Version: 2.1
Name: wasm-spec-kernel
Version: 0.1.1
Summary: A Jupyter kernel for the Wasm reference interpreter
Home-page: https://github.com/awendland/wasm_spec_kernel
License: BSD-3-Clause
Author: Alex Wendland
Author-email: me@alexwendland.com
Requires-Python: >=3.6.2,<4.0.0
Classifier: Framework :: IPython
Classifier: License :: OSI Approved :: BSD License
Classifier: Programming Language :: Python :: 3
Classifier: Programming Language :: Python :: 3.7
Classifier: Programming Language :: Python :: 3.8
Classifier: Programming Language :: Python :: 3.9
Classifier: Topic :: System :: Shells
Requires-Dist: pexpect (>=4.8.0,<5.0.0)
Project-URL: Repository, https://github.com/awendland/wasm_spec_kernel.git
